esa_snappy/__init__.py
esa_snappy/snappyutil.py
esa_snappy/examples/__init__.py
esa_snappy/examples/snappy_bmaths.py
esa_snappy/examples/snappy_flh.py
esa_snappy/examples/snappy_geo_roi.py
esa_snappy/examples/snappy_ndvi.py
esa_snappy/examples/snappy_ndvi_with_masks.py
esa_snappy/examples/snappy_reader_writer_formats.py
esa_snappy/examples/snappy_subset.py
esa_snappy/examples/snappy_write_image.py
esa_snappy/lib/jpy-1.0.0-cp39-cp39-macosx_12_0_universal2.whl
esa_snappy/lib/jpy-1.0.0-cp39-cp39-manylinux_2_17_aarch64.manylinux2014_aarch64.whl
esa_snappy/lib/jpy-1.0.0-cp39-cp39-manylinux_2_17_x86_64.manylinux2014_x86_64.whl
esa_snappy/lib/jpy-1.0.0-cp39-cp39-win_amd64.whl
esa_snappy/snapista/__init__.py
esa_snappy/snapista/graph.py
esa_snappy/snapista/graph_io.py
esa_snappy/snapista/operator.py
esa_snappy/snapista/operatorparams.py
esa_snappy/snapista/target_band.py
esa_snappy/snapista/target_band_descriptors.py
esa_snappy/snapista/binning/__init__.py
esa_snappy/snapista/binning/aggregator_avg.py
esa_snappy/snapista/binning/aggregator_avg_outlier.py
esa_snappy/snapista/binning/aggregator_minmax.py
esa_snappy/snapista/binning/aggregator_on_max_set.py
esa_snappy/snapista/binning/aggregator_percentile.py
esa_snappy/snapista/binning/aggregator_sum.py
esa_snappy/snapista/binning/aggregators.py
esa_snappy/snapista/binning/binning_band.py
esa_snappy/snapista/binning/binning_variable.py
esa_snappy/snapista/binning/binning_variables.py
esa_snappy/snapista/binning/output_bands.py
esa_snappy/snapista/demo/snapista-demo-bandmaths.ipynb
esa_snappy/snapista/demo/snapista-demo-binning.ipynb
esa_snappy/snapista/demo/data/subset_0_of_S3A_OL_1_ERR____20160701T092853_20160701T093053_20170919T102725_0119_006_036______MR1_R_NT_002.nc
esa_snappy/snapista/demo/data/subset_1_of_S3A_OL_2_WRR____20210304T082509_20210304T090900_20210609T141823_2631_069_121______MAR_R_NT_003.nc
esa_snappy-1.1.0.dist-info/licenses/LICENSE
esa_snappy-1.1.0.dist-info/METADATA
esa_snappy-1.1.0.dist-info/WHEEL
esa_snappy-1.1.0.dist-info/top_level.txt
esa_snappy-1.1.0.dist-info/RECORD
